jaeger_model_proto.cpython-39-x86_64-linux-gnu.so
jaeger_model_proto-0.1.2.dist-info/top_level.txt
jaeger_model_proto-0.1.2.dist-info/WHEEL
jaeger_model_proto-0.1.2.dist-info/LICENSE
jaeger_model_proto-0.1.2.dist-info/METADATA
jaeger_model_proto-0.1.2.dist-info/RECORD
